qiutil/__init__.py
qiutil/ast_config.py
qiutil/collections.py
qiutil/command.py
qiutil/dictionary_hierarchy.py
qiutil/file.py
qiutil/logging.py
qiutil/which.py
qiutil-2.1.4.dist-info/DESCRIPTION.rst
qiutil-2.1.4.dist-info/METADATA
qiutil-2.1.4.dist-info/metadata.json
qiutil-2.1.4.dist-info/RECORD
qiutil-2.1.4.dist-info/top_level.txt
qiutil-2.1.4.dist-info/WHEEL
