Metadata-Version: 2.0
Name: qiutil
Version: 2.1.4
Summary: Quantitative Imaging helper utilities.
Home-page: https://github.com/ohsu-qin/qiutil
Author: OHSU Knight Cancer Institute
Author-email: loneyf@ohsu.edu
License: MIT
Keywords: Imaging QIN
Platform: Any
Classifier: Development Status :: 5 - Production/Stable
Classifier: Topic :: Scientific/Engineering :: Bio-Informatics
Classifier: Environment :: Console
Classifier: Intended Audience :: Science/Research
Classifier: License :: OSI Approved :: MIT License
Classifier: Operating System :: OS Independent
Classifier: Programming Language :: Python
Requires-Dist: nose (==1.3.0)
Requires-Dist: PyYAML (==3.11)
Requires-Dist: Sphinx (==1.2.2)
